mcmax/__init__.py
mcmax/_version.py
mcmax/mcmax.py
tangods_mcmax-1.0.4.dist-info/LICENSE
tangods_mcmax-1.0.4.dist-info/METADATA
tangods_mcmax-1.0.4.dist-info/WHEEL
tangods_mcmax-1.0.4.dist-info/entry_points.txt
tangods_mcmax-1.0.4.dist-info/top_level.txt
tangods_mcmax-1.0.4.dist-info/RECORD
