Metadata-Version: 2.2
Name: tangods-mcmax
Version: 1.0.4
Summary: A tango device server to control the microcontrollers in the project MC-MAX
Author-email: Antonio Bartalesi <antonio.bartalesi@gmail.com>, Laura Torres Garcia <lautg88@gmail.com>
Project-URL: repository, https://gitlab.com/ABartalesi/mc-max-tango-device-server
Classifier: License :: OSI Approved :: GNU General Public License v3 or later (GPLv3+)
License-File: LICENSE
Requires-Dist: pytango>=9.5
Requires-Dist: paho-mqtt>=2.0
Provides-Extra: test
Requires-Dist: pytest; extra == "test"
